findawspeers/__init__.py
findawspeers/__main__.py
findawspeers-1.0.0.dist-info/DESCRIPTION.rst
findawspeers-1.0.0.dist-info/METADATA
findawspeers-1.0.0.dist-info/RECORD
findawspeers-1.0.0.dist-info/WHEEL
findawspeers-1.0.0.dist-info/entry_points.txt
findawspeers-1.0.0.dist-info/metadata.json
findawspeers-1.0.0.dist-info/top_level.txt
