Metadata-Version: 2.0
Name: findawspeers
Version: 1.0.0
Summary: Small utility to returns a list of this instances EC2 peers in an Auto scaling group
Home-page: https://github.com/drewsonne/findawspeers
Author: Drew J. Sonne
Author-email: drew.sonne@gmail.com
License: GPLv2
Platform: UNKNOWN
Requires-Dist: aws-auth-helper
Requires-Dist: boto
Requires-Dist: typing
